mercor_service_client/__init__.py
mercor_service_client/client.py
mercor_service_client-0.1.0.dist-info/METADATA
mercor_service_client-0.1.0.dist-info/WHEEL
mercor_service_client-0.1.0.dist-info/top_level.txt
mercor_service_client-0.1.0.dist-info/RECORD
